{
  "variants": {
    "facing=east,type=0": {
      "model": "thingamajigs:bases/huge_sign",
      "y": 90
    },
    "facing=north,type=0": {
      "model": "thingamajigs:bases/huge_sign"
    },
    "facing=south,type=0": {
      "model": "thingamajigs:bases/huge_sign",
      "y": 180
    },
    "facing=west,type=0": {
      "model": "thingamajigs:bases/huge_sign",
      "y": 270
    },
    "facing=east,type=1": {
      "model": "thingamajigs:block/other_overunder_sized_signs/toll_ahead_payments_accepted_sign",
      "y": 90
    },
    "facing=north,type=1": {
      "model": "thingamajigs:block/other_overunder_sized_signs/toll_ahead_payments_accepted_sign"
    },
    "facing=south,type=1": {
      "model": "thingamajigs:block/other_overunder_sized_signs/toll_ahead_payments_accepted_sign",
      "y": 180
    },
    "facing=west,type=1": {
      "model": "thingamajigs:block/other_overunder_sized_signs/toll_ahead_payments_accepted_sign",
      "y": 270
    }
  }
}